Workbook

Sheet Leia primeiro
D2: Kit Preço Certo
D3: Calculadora de preço para quem vende serviços
D4: Fórmulas prontas: é só preencher as células amarelas. Não precisa saber Excel.
B8: Comece em 3 passos
B10: 1 | C10: Descubra o custo da sua hora | J10: Abrir aba →
C11: Aba “Meu custo por hora”: preencha as células amarelas com seus gastos do mês, o quanto quer tirar para você e suas horas de trabalho.
B13: 2 | C13: Cadastre seus serviços | J13: Abrir aba →
C14: Aba “Meus serviços”: escreva o serviço, o tempo, o material gasto e o preço que você cobra hoje.
B16: 3 | C16: Veja o preço certo de cada um | J16: Ver painel →
C17: Você recebe o preço sugerido, o lucro de hoje e um aviso quando um serviço está dando prejuízo. Veja o resumo no “Meu Painel” e copie a “Tabela para divulgar”.
B19: Como ler as cores
B20: Você preenche | E20: Células amarelas: são as únicas que você edita.
B21: Calculado | E21: Fórmulas automáticas. Não precisa mexer.
B22: Resultado | E22: Preço sugerido e resultados principais, calculados sozinhos.
B24: Importante
B25: ✦ Os números que já estão preenchidos são EXEMPLOS ilustrativos, para você ver a conta funcionando. Troque pelos seus.
B26: ✦ A calculadora mostra a conta do preço. Ela não promete ganho nem resultado: o resultado depende dos seus custos e da sua demanda.
B27: ✦ Impostos: se você é MEI, coloque o valor do DAS mensal nos gastos fixos. Confirme o valor atual no portal oficial do MEI.
B28: ✦ Ferramenta de apoio. Não substitui a orientação de um contador.
B31: Kit Preço Certo · kitprecocerto.com.br

Sheet Meu custo por hora
A1: Passo 1 · Quanto custa a sua hora
A2: Preencha só as células amarelas. As contas já estão prontas. Os valores preenchidos são exemplos: troque pelos seus.
A4: Gastos fixos do mês (R$)
A5: Aluguel / cadeira / espaço | B5: 900 | C5: Se atende em casa, ponha 0 ou uma parte do aluguel
A6: Luz, água, internet | B6: 200
A7: Imposto (ex.: DAS do MEI) | B7: 80 | C7: Exemplo. Confira o valor atual no portal do MEI
A8: Telefone / aplicativos / agenda | B8: 80
A9: Divulgação (anúncios, cartões, etc.) | B9: 100
A10: Reposição de equipamentos (lixa, alicate) | B10: 120 | C10: Média mensal
A11: Outros gastos fixos | B11: 0
A12: Total de gastos fixos | B12: =SUM(B5:B11)
A14: O quanto você quer tirar para você
A15: Retirada mensal desejada (seu salário) | B15: 5000 | C15: É o que você quer ganhar por mês, além dos gastos
A17: Seu tempo de trabalho
A18: Horas de atendimento por dia | B18: 6 | C18: Horas em que está no local, disponível
A19: Dias trabalhados por semana | B19: 5
A20: Taxa de ocupação da agenda (%) | B20: 0.65 | C20: Parte das horas em que há cliente. Seja realista (50–80%)
A22: Resultado
A23: Semanas por mês (média) | B23: 4.33 | C23: Valor fixo: 52 semanas ÷ 12 meses
A24: Horas vendáveis por mês | B24: =B18*B19*B23*B20
A25: CUSTO DA SUA HORA (gastos + retirada) | B25: =IFERROR((B12+B15)/B24,0) | C25: Esse valor entra sozinho na aba “Meus serviços”
A27: Taxas e margem (valem para todos os serviços)
A28: Taxa da maquininha/cartão (%) | B28: 0.04 | C28: Veja a taxa da sua maquininha
A29: Margem de segurança / reserva (%) | B29: 0.1 | C29: Sobra extra no preço, para imprevistos. Pode deixar 0%
A31: Pronto! Próximo passo: cadastrar seus serviços →

Sheet Meus serviços
A1: Passo 2 · Preço sugerido por serviço | G1: Próximo: Meu Painel →
A2: Preencha as células amarelas (A a D). O PREÇO SUGERIDO aparece sozinho ao lado. Os serviços abaixo são EXEMPLOS: troque pelos seus.
A4: Serviço | B4: Tempo (min) | C4: Material (R$) | D4: Cobro hoje (R$) | E4: PREÇO SUGERIDO (R$) | F4: Situação | G4: Custo do tempo (R$) | H4: Custo total (R$) | I4: Lucro hoje (R$)
A5: Corte feminino | B5: 60 | C5: 10 | D5: 105 | E5: =IF(B5="","",ROUNDUP(H5/(1-'Meu custo por hora'!$B$28-'Meu custo por hora'!$B$29),0)) | F5: =IF(OR(B5="",D5=""),"",IF(D5>=E5,"OK: cobre custos e margem",IF(I5>=0,"Atenção: pouca folga","PREJUÍZO: abaixo do custo"))) | G5: =IF(B5="","",B5/60*'Meu custo por hora'!$B$25) | H5: =IF(B5="","",G5+C5) | I5: =IF(OR(B5="",D5=""),"",D5*(1-'Meu custo por hora'!$B$28)-H5)
A6: Escova | B6: 45 | C6: 8 | D6: 70 | E6: =IF(B6="","",ROUNDUP(H6/(1-'Meu custo por hora'!$B$28-'Meu custo por hora'!$B$29),0)) | F6: =IF(OR(B6="",D6=""),"",IF(D6>=E6,"OK: cobre custos e margem",IF(I6>=0,"Atenção: pouca folga","PREJUÍZO: abaixo do custo"))) | G6: =IF(B6="","",B6/60*'Meu custo por hora'!$B$25) | H6: =IF(B6="","",G6+C6) | I6: =IF(OR(B6="",D6=""),"",D6*(1-'Meu custo por hora'!$B$28)-H6)
A7: Manicure em gel | B7: 60 | C7: 15 | D7: 90 | E7: =IF(B7="","",ROUNDUP(H7/(1-'Meu custo por hora'!$B$28-'Meu custo por hora'!$B$29),0)) | F7: =IF(OR(B7="",D7=""),"",IF(D7>=E7,"OK: cobre custos e margem",IF(I7>=0,"Atenção: pouca folga","PREJUÍZO: abaixo do custo"))) | G7: =IF(B7="","",B7/60*'Meu custo por hora'!$B$25) | H7: =IF(B7="","",G7+C7) | I7: =IF(OR(B7="",D7=""),"",D7*(1-'Meu custo por hora'!$B$28)-H7)
A8: Design de sobrancelha | B8: 30 | C8: 5 | D8: 55 | E8: =IF(B8="","",ROUNDUP(H8/(1-'Meu custo por hora'!$B$28-'Meu custo por hora'!$B$29),0)) | F8: =IF(OR(B8="",D8=""),"",IF(D8>=E8,"OK: cobre custos e margem",IF(I8>=0,"Atenção: pouca folga","PREJUÍZO: abaixo do custo"))) | G8: =IF(B8="","",B8/60*'Meu custo por hora'!$B$25) | H8: =IF(B8="","",G8+C8) | I8: =IF(OR(B8="",D8=""),"",D8*(1-'Meu custo por hora'!$B$28)-H8)
A9: Limpeza de pele | B9: 75 | C9: 20 | D9: 140 | E9: =IF(B9="","",ROUNDUP(H9/(1-'Meu custo por hora'!$B$28-'Meu custo por hora'!$B$29),0)) | F9: =IF(OR(B9="",D9=""),"",IF(D9>=E9,"OK: cobre custos e margem",IF(I9>=0,"Atenção: pouca folga","PREJUÍZO: abaixo do custo"))) | G9: =IF(B9="","",B9/60*'Meu custo por hora'!$B$25) | H9: =IF(B9="","",G9+C9) | I9: =IF(OR(B9="",D9=""),"",D9*(1-'Meu custo por hora'!$B$28)-H9)
A10: Massagem relaxante | B10: 60 | C10: 10 | D10: 110 | E10: =IF(B10="","",ROUNDUP(H10/(1-'Meu custo por hora'!$B$28-'Meu custo por hora'!$B$29),0)) | F10: =IF(OR(B10="",D10=""),"",IF(D10>=E10,"OK: cobre custos e margem",IF(I10>=0,"Atenção: pouca folga","PREJUÍZO: abaixo do custo"))) | G10: =IF(B10="","",B10/60*'Meu custo por hora'!$B$25) | H10: =IF(B10="","",G10+C10) | I10: =IF(OR(B10="",D10=""),"",D10*(1-'Meu custo por hora'!$B$28)-H10)
A11: Extensão de cílios | B11: 120 | C11: 40 | D11: 230 | E11: =IF(B11="","",ROUNDUP(H11/(1-'Meu custo por hora'!$B$28-'Meu custo por hora'!$B$29),0)) | F11: =IF(OR(B11="",D11=""),"",IF(D11>=E11,"OK: cobre custos e margem",IF(I11>=0,"Atenção: pouca folga","PREJUÍZO: abaixo do custo"))) | G11: =IF(B11="","",B11/60*'Meu custo por hora'!$B$25) | H11: =IF(B11="","",G11+C11) | I11: =IF(OR(B11="",D11=""),"",D11*(1-'Meu custo por hora'!$B$28)-H11)
A12: Depilação (perna) | B12: 40 | C12: 10 | D12: 75 | E12: =IF(B12="","",ROUNDUP(H12/(1-'Meu custo por hora'!$B$28-'Meu custo por hora'!$B$29),0)) | F12: =IF(OR(B12="",D12=""),"",IF(D12>=E12,"OK: cobre custos e margem",IF(I12>=0,"Atenção: pouca folga","PREJUÍZO: abaixo do custo"))) | G12: =IF(B12="","",B12/60*'Meu custo por hora'!$B$25) | H12: =IF(B12="","",G12+C12) | I12: =IF(OR(B12="",D12=""),"",D12*(1-'Meu custo por hora'!$B$28)-H12)
E13: =IF(B13="","",ROUNDUP(H13/(1-'Meu custo por hora'!$B$28-'Meu custo por hora'!$B$29),0)) | F13: =IF(OR(B13="",D13=""),"",IF(D13>=E13,"OK: cobre custos e margem",IF(I13>=0,"Atenção: pouca folga","PREJUÍZO: abaixo do custo"))) | G13: =IF(B13="","",B13/60*'Meu custo por hora'!$B$25) | H13: =IF(B13="","",G13+C13) | I13: =IF(OR(B13="",D13=""),"",D13*(1-'Meu custo por hora'!$B$28)-H13)
E14: =IF(B14="","",ROUNDUP(H14/(1-'Meu custo por hora'!$B$28-'Meu custo por hora'!$B$29),0)) | F14: =IF(OR(B14="",D14=""),"",IF(D14>=E14,"OK: cobre custos e margem",IF(I14>=0,"Atenção: pouca folga","PREJUÍZO: abaixo do custo"))) | G14: =IF(B14="","",B14/60*'Meu custo por hora'!$B$25) | H14: =IF(B14="","",G14+C14) | I14: =IF(OR(B14="",D14=""),"",D14*(1-'Meu custo por hora'!$B$28)-H14)
E15: =IF(B15="","",ROUNDUP(H15/(1-'Meu custo por hora'!$B$28-'Meu custo por hora'!$B$29),0)) | F15: =IF(OR(B15="",D15=""),"",IF(D15>=E15,"OK: cobre custos e margem",IF(I15>=0,"Atenção: pouca folga","PREJUÍZO: abaixo do custo"))) | G15: =IF(B15="","",B15/60*'Meu custo por hora'!$B$25) | H15: =IF(B15="","",G15+C15) | I15: =IF(OR(B15="",D15=""),"",D15*(1-'Meu custo por hora'!$B$28)-H15)
E16: =IF(B16="","",ROUNDUP(H16/(1-'Meu custo por hora'!$B$28-'Meu custo por hora'!$B$29),0)) | F16: =IF(OR(B16="",D16=""),"",IF(D16>=E16,"OK: cobre custos e margem",IF(I16>=0,"Atenção: pouca folga","PREJUÍZO: abaixo do custo"))) | G16: =IF(B16="","",B16/60*'Meu custo por hora'!$B$25) | H16: =IF(B16="","",G16+C16) | I16: =IF(OR(B16="",D16=""),"",D16*(1-'Meu custo por hora'!$B$28)-H16)
E17: =IF(B17="","",ROUNDUP(H17/(1-'Meu custo por hora'!$B$28-'Meu custo por hora'!$B$29),0)) | F17: =IF(OR(B17="",D17=""),"",IF(D17>=E17,"OK: cobre custos e margem",IF(I17>=0,"Atenção: pouca folga","PREJUÍZO: abaixo do custo"))) | G17: =IF(B17="","",B17/60*'Meu custo por hora'!$B$25) | H17: =IF(B17="","",G17+C17) | I17: =IF(OR(B17="",D17=""),"",D17*(1-'Meu custo por hora'!$B$28)-H17)
E18: =IF(B18="","",ROUNDUP(H18/(1-'Meu custo por hora'!$B$28-'Meu custo por hora'!$B$29),0)) | F18: =IF(OR(B18="",D18=""),"",IF(D18>=E18,"OK: cobre custos e margem",IF(I18>=0,"Atenção: pouca folga","PREJUÍZO: abaixo do custo"))) | G18: =IF(B18="","",B18/60*'Meu custo por hora'!$B$25) | H18: =IF(B18="","",G18+C18) | I18: =IF(OR(B18="",D18=""),"",D18*(1-'Meu custo por hora'!$B$28)-H18)
E19: =IF(B19="","",ROUNDUP(H19/(1-'Meu custo por hora'!$B$28-'Meu custo por hora'!$B$29),0)) | F19: =IF(OR(B19="",D19=""),"",IF(D19>=E19,"OK: cobre custos e margem",IF(I19>=0,"Atenção: pouca folga","PREJUÍZO: abaixo do custo"))) | G19: =IF(B19="","",B19/60*'Meu custo por hora'!$B$25) | H19: =IF(B19="","",G19+C19) | I19: =IF(OR(B19="",D19=""),"",D19*(1-'Meu custo por hora'!$B$28)-H19)
E20: =IF(B20="","",ROUNDUP(H20/(1-'Meu custo por hora'!$B$28-'Meu custo por hora'!$B$29),0)) | F20: =IF(OR(B20="",D20=""),"",IF(D20>=E20,"OK: cobre custos e margem",IF(I20>=0,"Atenção: pouca folga","PREJUÍZO: abaixo do custo"))) | G20: =IF(B20="","",B20/60*'Meu custo por hora'!$B$25) | H20: =IF(B20="","",G20+C20) | I20: =IF(OR(B20="",D20=""),"",D20*(1-'Meu custo por hora'!$B$28)-H20)
E21: =IF(B21="","",ROUNDUP(H21/(1-'Meu custo por hora'!$B$28-'Meu custo por hora'!$B$29),0)) | F21: =IF(OR(B21="",D21=""),"",IF(D21>=E21,"OK: cobre custos e margem",IF(I21>=0,"Atenção: pouca folga","PREJUÍZO: abaixo do custo"))) | G21: =IF(B21="","",B21/60*'Meu custo por hora'!$B$25) | H21: =IF(B21="","",G21+C21) | I21: =IF(OR(B21="",D21=""),"",D21*(1-'Meu custo por hora'!$B$28)-H21)
E22: =IF(B22="","",ROUNDUP(H22/(1-'Meu custo por hora'!$B$28-'Meu custo por hora'!$B$29),0)) | F22: =IF(OR(B22="",D22=""),"",IF(D22>=E22,"OK: cobre custos e margem",IF(I22>=0,"Atenção: pouca folga","PREJUÍZO: abaixo do custo"))) | G22: =IF(B22="","",B22/60*'Meu custo por hora'!$B$25) | H22: =IF(B22="","",G22+C22) | I22: =IF(OR(B22="",D22=""),"",D22*(1-'Meu custo por hora'!$B$28)-H22)
E23: =IF(B23="","",ROUNDUP(H23/(1-'Meu custo por hora'!$B$28-'Meu custo por hora'!$B$29),0)) | F23: =IF(OR(B23="",D23=""),"",IF(D23>=E23,"OK: cobre custos e margem",IF(I23>=0,"Atenção: pouca folga","PREJUÍZO: abaixo do custo"))) | G23: =IF(B23="","",B23/60*'Meu custo por hora'!$B$25) | H23: =IF(B23="","",G23+C23) | I23: =IF(OR(B23="",D23=""),"",D23*(1-'Meu custo por hora'!$B$28)-H23)
E24: =IF(B24="","",ROUNDUP(H24/(1-'Meu custo por hora'!$B$28-'Meu custo por hora'!$B$29),0)) | F24: =IF(OR(B24="",D24=""),"",IF(D24>=E24,"OK: cobre custos e margem",IF(I24>=0,"Atenção: pouca folga","PREJUÍZO: abaixo do custo"))) | G24: =IF(B24="","",B24/60*'Meu custo por hora'!$B$25) | H24: =IF(B24="","",G24+C24) | I24: =IF(OR(B24="",D24=""),"",D24*(1-'Meu custo por hora'!$B$28)-H24)
... E29: =IF(B29="","",ROUNDUP(H29/(1-'Meu custo por hora'!$B$28-'Meu custo por hora'!$B$29),0)) | F29: =IF(OR(B29="",D29=""),"",IF(D29>=E29,"OK: cobre custos e margem",IF(I29>=0,"Atenção: pouca folga","PREJUÍZO: abaixo do custo"))) | G29: =IF(B29="","",B29/60*'Meu custo por hora'!$B$25) | H29: =IF(B29="","",G29+C29) | I29: =IF(OR(B29="",D29=""),"",D29*(1-'Meu custo por hora'!$B$28)-H29)
A31: ✦ Como o preço é calculado: (custo do tempo + material) ÷ (1 − taxa do cartão − margem), arredondado para cima ao real.
A32: ✦ Custo do tempo = minutos ÷ 60 × custo da sua hora (aba “Meu custo por hora”). As colunas de conta ficam à direita (G a I).
A33: ✦ Lucro hoje = o que você cobra, menos a taxa do cartão, menos o custo total. Negativo = você paga para fazer esse serviço.
A34: ✦ Tempos e materiais dos exemplos são ilustrativos. Meça os seus: cronometre 3 atendimentos e anote o que gastou.

Sheet Meu Painel
A1: Seu painel de preços | K1: Ver Tabela para divulgar →
A2: Resumo automático feito com o que você preencheu nas abas anteriores. Aqui você não digita nada.
B5: CUSTO DA SUA HORA | E5: SERVIÇOS CADASTRADOS | H5: PEDEM REAJUSTE | K5: DANDO PREJUÍZO
B6: ='Meu custo por hora'!B25 | E6: =COUNT('Meus serviços'!B5:B29) | H6: =COUNTIF('Meus serviços'!F5:F29,"Atenção*")+COUNTIF('Meus serviços'!F5:F29,"PREJUÍZO*") | K6: =COUNTIF('Meus serviços'!F5:F29,"PREJUÍZO*")
B7: gastos + sua retirada | E7: na aba Meus serviços | H7: pouca folga ou prejuízo | K7: preço abaixo do custo
B9: SERVIÇOS OK | E9: LUCRO MÉDIO HOJE | H9: MAIS LUCRATIVO | K9: PEDE MAIS ATENÇÃO
B10: =COUNTIF('Meus serviços'!F5:F29,"OK*") | E10: =IFERROR(AVERAGE('Meus serviços'!I5:I29),0) | H10: =IFERROR(INDEX('Meus serviços'!A5:A29,MATCH(MAX('Meus serviços'!I5:I29),'Meus serviços'!I5:I29,0)),"-") | K10: =IFERROR(INDEX('Meus serviços'!A5:A29,MATCH(MIN('Meus serviços'!I5:I29),'Meus serviços'!I5:I29,0)),"-")
B11: cobrem custos e margem | E11: por atendimento, após a maquininha | H11: maior lucro por atendimento | K11: menor lucro por atendimento
B13: =IF(K6>0,"Atenção: "&K6&" serviço(s) estão com preço abaixo do custo. Veja o preço sugerido na aba Meus serviços.",IF(H6>0,"Alguns serviços têm pouca folga. Compare o preço de hoje com o preço sugerido.","Os preços cadastrados cobrem seus custos e a margem. Revise quando seus gastos mudarem."))
B15: Quanto você cobra hoje × preço sugerido
B36: ✦ O gráfico mostra os 10 primeiros serviços da aba “Meus serviços”.

Sheet Tabela para divulgar
A1: Tabela de preços
B3: Digite aqui o nome do seu studio (opcional)
B5: Serviço | C5: Preço
B6: =IF('Meus serviços'!B5="","",'Meus serviços'!A5) | C6: =IF('Meus serviços'!B5="","",IF('Meus serviços'!D5>='Meus serviços'!E5,'Meus serviços'!D5,'Meus serviços'!E5))
B7: =IF('Meus serviços'!B6="","",'Meus serviços'!A6) | C7: =IF('Meus serviços'!B6="","",IF('Meus serviços'!D6>='Meus serviços'!E6,'Meus serviços'!D6,'Meus serviços'!E6))
B8: =IF('Meus serviços'!B7="","",'Meus serviços'!A7) | C8: =IF('Meus serviços'!B7="","",IF('Meus serviços'!D7>='Meus serviços'!E7,'Meus serviços'!D7,'Meus serviços'!E7))
B9: =IF('Meus serviços'!B8="","",'Meus serviços'!A8) | C9: =IF('Meus serviços'!B8="","",IF('Meus serviços'!D8>='Meus serviços'!E8,'Meus serviços'!D8,'Meus serviços'!E8))
B10: =IF('Meus serviços'!B9="","",'Meus serviços'!A9) | C10: =IF('Meus serviços'!B9="","",IF('Meus serviços'!D9>='Meus serviços'!E9,'Meus serviços'!D9,'Meus serviços'!E9))
B11: =IF('Meus serviços'!B10="","",'Meus serviços'!A10) | C11: =IF('Meus serviços'!B10="","",IF('Meus serviços'!D10>='Meus serviços'!E10,'Meus serviços'!D10,'Meus serviços'!E10))
B12: =IF('Meus serviços'!B11="","",'Meus serviços'!A11) | C12: =IF('Meus serviços'!B11="","",IF('Meus serviços'!D11>='Meus serviços'!E11,'Meus serviços'!D11,'Meus serviços'!E11))
B13: =IF('Meus serviços'!B12="","",'Meus serviços'!A12) | C13: =IF('Meus serviços'!B12="","",IF('Meus serviços'!D12>='Meus serviços'!E12,'Meus serviços'!D12,'Meus serviços'!E12))
B14: =IF('Meus serviços'!B13="","",'Meus serviços'!A13) | C14: =IF('Meus serviços'!B13="","",IF('Meus serviços'!D13>='Meus serviços'!E13,'Meus serviços'!D13,'Meus serviços'!E13))
B15: =IF('Meus serviços'!B14="","",'Meus serviços'!A14) | C15: =IF('Meus serviços'!B14="","",IF('Meus serviços'!D14>='Meus serviços'!E14,'Meus serviços'!D14,'Meus serviços'!E14))
B16: =IF('Meus serviços'!B15="","",'Meus serviços'!A15) | C16: =IF('Meus serviços'!B15="","",IF('Meus serviços'!D15>='Meus serviços'!E15,'Meus serviços'!D15,'Meus serviços'!E15))
B17: =IF('Meus serviços'!B16="","",'Meus serviços'!A16) | C17: =IF('Meus serviços'!B16="","",IF('Meus serviços'!D16>='Meus serviços'!E16,'Meus serviços'!D16,'Meus serviços'!E16))
... B30: =IF('Meus serviços'!B29="","",'Meus serviços'!A29) | C30: =IF('Meus serviços'!B29="","",IF('Meus serviços'!D29>='Meus serviços'!E29,'Meus serviços'!D29,'Meus serviços'!E29))
B32: Kit Preço Certo · kitprecocerto.com.br
B33: A tabela usa o maior valor entre o que você cobra hoje e o preço sugerido. Tire um print e poste.
